hestia_earth/__init__.py
hestia_earth/orchestrator/__init__.py
hestia_earth/orchestrator/log.py
hestia_earth/orchestrator/utils.py
hestia_earth/orchestrator/version.py
hestia_earth/orchestrator/models/__init__.py
hestia_earth/orchestrator/models/transformations.py
hestia_earth/orchestrator/models/emissions/__init__.py
hestia_earth/orchestrator/models/emissions/deleted.py
hestia_earth/orchestrator/strategies/__init__.py
hestia_earth/orchestrator/strategies/merge/__init__.py
hestia_earth/orchestrator/strategies/merge/merge_append.py
hestia_earth/orchestrator/strategies/merge/merge_default.py
hestia_earth/orchestrator/strategies/merge/merge_list.py
hestia_earth/orchestrator/strategies/merge/merge_node.py
hestia_earth/orchestrator/strategies/run/__init__.py
hestia_earth/orchestrator/strategies/run/add_blank_node_if_missing.py
hestia_earth/orchestrator/strategies/run/add_key_if_missing.py
hestia_earth/orchestrator/strategies/run/always.py
tests/models/__init__.py
tests/models/test_transformations.py
tests/models/emissions/__init__.py
tests/models/emissions/test_deleted.py
tests/strategies/__init__.py
tests/strategies/merge/__init__.py
tests/strategies/merge/test_merge_append.py
tests/strategies/merge/test_merge_default.py
tests/strategies/merge/test_merge_list.py
tests/strategies/merge/test_merge_node.py
tests/strategies/run/__init__.py
tests/strategies/run/test_add_blank_node_if_missing.py
tests/strategies/run/test_add_key_if_missing.py
tests/strategies/run/test_always.py
hestia_earth_orchestrator-0.6.20.dist-info/LICENSE
hestia_earth_orchestrator-0.6.20.dist-info/METADATA
hestia_earth_orchestrator-0.6.20.dist-info/WHEEL
hestia_earth_orchestrator-0.6.20.dist-info/top_level.txt
hestia_earth_orchestrator-0.6.20.dist-info/RECORD
