Metadata-Version: 2.1
Name: hestia-earth-orchestrator
Version: 0.6.20
Summary: Hestia's module to orchestrate the models.
Home-page: https://gitlab.com/hestia-earth/hestia-engine-orchestrator
Author: Hestia Team
Author-email: guillaumeroyer.mail@gmail.com
License: MIT
Platform: UNKNOWN
Classifier: License :: OSI Approved :: GNU General Public License v3 (GPLv3)
Classifier: Programming Language :: Python :: 3.6
License-File: LICENSE
Requires-Dist: pydash
Requires-Dist: hestia-earth.utils>=0.13.11
Requires-Dist: hestia-earth.schema>=30.0.0
